{
  "source": "yfinance",
  "universe_id": "djia",
  "display_name": "DJIA Constituents",
  "requested_tickers": [
    "AAPL",
    "AMGN",
    "AMZN",
    "AXP",
    "BA",
    "CAT",
    "CRM",
    "CSCO",
    "CVX",
    "DIS",
    "GS",
    "HD",
    "HON",
    "IBM",
    "JNJ",
    "JPM",
    "KO",
    "MCD",
    "MMM",
    "MRK",
    "MSFT",
    "NKE",
    "NVDA",
    "PG",
    "SHW",
    "TRV",
    "UNH",
    "V",
    "VZ",
    "WMT"
  ],
  "available_tickers": [
    "AAPL",
    "AMGN",
    "AMZN",
    "AXP",
    "BA",
    "CAT",
    "CRM",
    "CSCO",
    "CVX",
    "DIS",
    "GS",
    "HD",
    "HON",
    "IBM",
    "JNJ",
    "JPM",
    "KO",
    "MCD",
    "MMM",
    "MRK",
    "MSFT",
    "NKE",
    "NVDA",
    "PG",
    "SHW",
    "TRV",
    "UNH",
    "V",
    "VZ",
    "WMT"
  ],
  "construction_date": "2020-06-01",
  "estimation_months": 36,
  "universe_name": "djia_20200601_36m",
  "output_dir": "C:\\Users\\narro\\Desktop\\semestre\\honores_actuaria\\outputs\\final_experimental_setup\\framework_runs\\djia_20200601_36m",
  "frequency": "B",
  "start": "2017-05-25 00:00:00",
  "end": "2021-06-08 00:00:00"
}